{
    "jugadores": [
        {
            "nombre": "Juan Perez",
            "nivel": "C",
            "goles": 10,
            "sueldo": 50000,
            "bono": 25000,
            "equipo": "rojo"
        },
        {
            "nombre": "EL Cuauh",
            "nivel": "Cuauh",
            "goles": 30,
            "sueldo": 100000,
            "bono": 30000,
            "equipo": "azul"
        },
        {
            "nombre": "Cosme Fulanito",
            "nivel": "A",
            "goles": 7,
            "sueldo": 20000,
            "bono": 10000,
            "equipo": "azul"
        },
        {
            "nombre": "El Rulo",
            "nivel": "B",
            "goles": 9,
            "sueldo": 30000,
            "bono": 15000,
            "equipo": "rojo"
        }
    ],
    "equipo": [
        {
            "nombre": "rojo",
            "niveles": {
                "A": 5,
                "B": 10,
                "C": 15,
                "Cuauh": 20
            }
        },
        {
            "nombre": "azul",
            "niveles": {
                "A": 5,
                "B": 10,
                "C": 15,
                "Cuauh": 20
            }
        }
    ]
}